monero_health/__init__.py
monero_health/monero_health.py
monero_health-1.1.5.dist-info/LICENSE
monero_health-1.1.5.dist-info/METADATA
monero_health-1.1.5.dist-info/WHEEL
monero_health-1.1.5.dist-info/top_level.txt
monero_health-1.1.5.dist-info/RECORD
