Metadata-Version: 2.1
Name: monero-health
Version: 1.1.5
Summary: Check health of monero daemons.
Home-page: https://github.com/monero-ecosystem/monero_health
Author: Norman Moeschter-Schenck
Author-email: norman.moeschter@gmail.com
Maintainer: Norman Moeschter-Schenck
Maintainer-email: <norman.moeschter@gmail.com>
License: UNKNOWN
Download-URL: https://github.com/monero-ecosystem/monero_health/archive/v1.1.5.tar.gz
Platform: UNKNOWN
Classifier: Development Status :: 5 - Production/Stable
Classifier: Intended Audience :: Developers
Classifier: License :: OSI Approved :: MIT License
Classifier: Natural Language :: English
Classifier: Programming Language :: Python
Requires-Dist: python-monerorpc (>=0.5.12)
Requires-Dist: monero-scripts (>=0.0.7)
Provides-Extra: test
Requires-Dist: mock ; extra == 'test'
Requires-Dist: pytest ; extra == 'test'
